cogs/send/__init__.py
d_snek_cogs_send-0.0.1b1.dist-info/METADATA
d_snek_cogs_send-0.0.1b1.dist-info/WHEEL
d_snek_cogs_send-0.0.1b1.dist-info/top_level.txt
d_snek_cogs_send-0.0.1b1.dist-info/RECORD
