Metadata-Version: 2.1
Name: d-snek-cogs-send
Version: 0.0.1b1
Summary: Discord SNEK Cog; Send
Home-page: https://git.jboi.dev/ShadowJonathan/snek-send
Author: Jonathan de Jong
Author-email: jonathan@automatia.nl
License: UNKNOWN
Platform: UNKNOWN
Classifier: Programming Language :: Python :: 3
Classifier: License :: OSI Approved :: MIT License
Classifier: Operating System :: OS Independent
Requires-Python: >=3.6
Requires-Dist: d-snek (>=1.2.4)
Requires-Dist: discord.py (>=1.2.5)
Requires-Dist: emoji (>=0.5.4)
Provides-Extra: dev
Requires-Dist: ipython ; extra == 'dev'
Requires-Dist: twine ; extra == 'dev'
